{
  "messageId": "19ee13ad7d4af203",
  "threadId": "19ee13ad7d4af203",
  "display_url": "https://mail.google.com/mail/u/0/#inbox/19ee13ad7d4af203",
  "subject": "VIDEO - Crypto Flips NYSE",
  "from": "InvestAnswers <investanswers@creator.patreon.com>",
  "to": "samin@aianswer.us",
  "cc": "",
  "date_header": "Fri, 19 Jun 2026 18:53:09 +0000",
  "date_iso": "2026-06-19T18:53:09+00:00",
  "message_id_header": "<20260619185309.7fc1f112962eedbb@creator.patreon.com>",
  "labelIds": [
    "CATEGORY_PROMOTIONS",
    "UNREAD",
    "INBOX"
  ],
  "snippet": "Live at 12pm Pacific: https://youtube.com/live/UFjg3x2zWP4... ͏ ͏ ͏ ͏ ͏ ͏ ͏ ͏ ͏ ͏ ͏ ͏ ͏ ͏ ͏ ͏ ͏ ͏ ͏ ͏ ͏ ͏ ͏ ͏ ͏ ͏ ͏ ͏ ͏ ͏ ͏ ͏ ͏ ͏ ͏ ͏ ͏ ͏ ͏ ͏ ͏ ͏ ͏ ͏ ͏ ͏ ͏ ͏ ͏ ͏ ͏ ͏ ͏ ͏ ͏ ͏ ͏ ͏ ͏ ͏ ͏ ͏ ͏ ͏ ͏ ͏ ͏ ͏ ͏ ͏",
  "filename_base": "2026-06-19_185309_VIDEO-Crypto-Flips-NYSE_19ee13ad7d4af203_14c2cf24",
  "raw_path": "emails/raw_eml/2026-06-19_185309_VIDEO-Crypto-Flips-NYSE_19ee13ad7d4af203_14c2cf24.eml",
  "text_path": "emails/text_md/2026-06-19_185309_VIDEO-Crypto-Flips-NYSE_19ee13ad7d4af203_14c2cf24.md",
  "meta_path": "emails/metadata/2026-06-19_185309_VIDEO-Crypto-Flips-NYSE_19ee13ad7d4af203_14c2cf24.json",
  "text_chars": 1871,
  "raw_bytes": 55579,
  "sizeEstimate": 55579,
  "attachments": []
}
