{
  "messageId": "19e1efc77527fd5f",
  "threadId": "19e1efc77527fd5f",
  "display_url": "https://mail.google.com/mail/u/0/#inbox/19e1efc77527fd5f",
  "subject": "Don't even think about Refinancing a Mtg Today",
  "from": "InvestAnswers <investanswers@creator.patreon.com>",
  "to": "samin@aianswer.us",
  "cc": "",
  "date_header": "Wed, 13 May 2026 01:38:41 +0000",
  "date_iso": "2026-05-13T01:38:41+00:00",
  "message_id_header": "<20260513013841.1d6edfc307b5af16@creator.patreon.com>",
  "labelIds": [
    "CATEGORY_PROMOTIONS",
    "UNREAD",
    "INBOX"
  ],
  "snippet": "The US 30-Year Yield is now 5.03%. Only 4 other times in recent history was it this high. 30-year fixed mortgage rates track the long end of the cur... ͏ ͏ ͏ ͏ ͏ ͏ ͏ ͏ ͏ ͏ ͏ ͏ ͏ ͏ ͏ ͏ ͏ ͏ ͏ ͏ ͏ ͏ ͏ ͏ ͏",
  "filename_base": "2026-05-13_013841_Dont-even-think-about-Refinancing-a-Mtg-Today_19e1efc77527fd5f_04c7383f",
  "raw_path": "emails/raw_eml/2026-05-13_013841_Dont-even-think-about-Refinancing-a-Mtg-Today_19e1efc77527fd5f_04c7383f.eml",
  "text_path": "emails/text_md/2026-05-13_013841_Dont-even-think-about-Refinancing-a-Mtg-Today_19e1efc77527fd5f_04c7383f.md",
  "meta_path": "emails/metadata/2026-05-13_013841_Dont-even-think-about-Refinancing-a-Mtg-Today_19e1efc77527fd5f_04c7383f.json",
  "text_chars": 2134,
  "raw_bytes": 52824,
  "sizeEstimate": 52824,
  "attachments": []
}
