{
  "messageId": "19e95fbd1351bdc9",
  "threadId": "19e95fbd1351bdc9",
  "display_url": "https://mail.google.com/mail/u/0/#inbox/19e95fbd1351bdc9",
  "subject": "ARK did some bottom fishing today",
  "from": "InvestAnswers <investanswers@creator.patreon.com>",
  "to": "samin@aianswer.us",
  "cc": "",
  "date_header": "Fri, 05 Jun 2026 04:12:47 +0000",
  "date_iso": "2026-06-05T04:12:47+00:00",
  "message_id_header": "<20260605041247.ad49f7d638dd0af2@creator.patreon.com>",
  "labelIds": [
    "CATEGORY_PROMOTIONS",
    "UNREAD",
    "INBOX"
  ],
  "snippet": "I own BABA and AVGO. COIN and CRCL are cheap.... I always felt ACHR was a fraudulent company. BIDU is other side of the BABA coin... ... ͏ ͏ ͏ ͏ ͏ ͏ ͏ ͏ ͏ ͏ ͏ ͏ ͏ ͏ ͏ ͏ ͏ ͏ ͏ ͏ ͏ ͏ ͏ ͏ ͏ ͏ ͏ ͏ ͏ ͏ ͏ ͏",
  "filename_base": "2026-06-05_041247_ARK-did-some-bottom-fishing-today_19e95fbd1351bdc9_210ca448",
  "raw_path": "emails/raw_eml/2026-06-05_041247_ARK-did-some-bottom-fishing-today_19e95fbd1351bdc9_210ca448.eml",
  "text_path": "emails/text_md/2026-06-05_041247_ARK-did-some-bottom-fishing-today_19e95fbd1351bdc9_210ca448.md",
  "meta_path": "emails/metadata/2026-06-05_041247_ARK-did-some-bottom-fishing-today_19e95fbd1351bdc9_210ca448.json",
  "text_chars": 1924,
  "raw_bytes": 52596,
  "sizeEstimate": 52596,
  "attachments": []
}
