{
  "messageId": "19e43b21d01fb93c",
  "threadId": "19e43b21d01fb93c",
  "display_url": "https://mail.google.com/mail/u/0/#inbox/19e43b21d01fb93c",
  "subject": "SpaceXAI S-1 drops tomorrow",
  "from": "InvestAnswers <investanswers@creator.patreon.com>",
  "to": "samin@aianswer.us",
  "cc": "",
  "date_header": "Wed, 20 May 2026 04:43:25 +0000",
  "date_iso": "2026-05-20T04:43:25+00:00",
  "message_id_header": "<20260520044325.42243176a553a261@creator.patreon.com>",
  "labelIds": [
    "CATEGORY_PROMOTIONS",
    "UNREAD",
    "INBOX"
  ],
  "snippet": "The setup is wild:• $2T valuation• $75B will be raised• Cash goes straight to the balance sheet• Elon confirmed he is not selling shares• Goldman Sach... ͏ ͏ ͏ ͏ ͏ ͏ ͏ ͏ ͏ ͏ ͏ ͏ ͏ ͏ ͏ ͏ ͏ ͏ ͏ ͏ ͏ ͏ ͏ ͏",
  "filename_base": "2026-05-20_044325_SpaceXAI-S-1-drops-tomorrow_19e43b21d01fb93c_f66cb0ef",
  "raw_path": "emails/raw_eml/2026-05-20_044325_SpaceXAI-S-1-drops-tomorrow_19e43b21d01fb93c_f66cb0ef.eml",
  "text_path": "emails/text_md/2026-05-20_044325_SpaceXAI-S-1-drops-tomorrow_19e43b21d01fb93c_f66cb0ef.md",
  "meta_path": "emails/metadata/2026-05-20_044325_SpaceXAI-S-1-drops-tomorrow_19e43b21d01fb93c_f66cb0ef.json",
  "text_chars": 2517,
  "raw_bytes": 53524,
  "sizeEstimate": 53524,
  "attachments": []
}
