{
  "messageId": "19e08433d10ae0c3",
  "threadId": "19e08433d10ae0c3",
  "display_url": "https://mail.google.com/mail/u/0/#inbox/19e08433d10ae0c3",
  "subject": "Tesla Rerating",
  "from": "InvestAnswers <investanswers@creator.patreon.com>",
  "to": "samin@aianswer.us",
  "cc": "",
  "date_header": "Fri, 08 May 2026 15:44:43 +0000",
  "date_iso": "2026-05-08T15:44:43+00:00",
  "message_id_header": "<20260508154443.e6a5e9cc6a1002b2@creator.patreon.com>",
  "labelIds": [
    "UNREAD",
    "CATEGORY_UPDATES",
    "INBOX"
  ],
  "snippet": "As promised, tesla being rerated. Stock up 27% last 30 days. Also seasonality, a month ago on Cyberbulls I called APRIL 7th the LOWPOINT. ... ͏ ͏ ͏ ͏ ͏ ͏ ͏ ͏ ͏ ͏ ͏ ͏ ͏ ͏ ͏ ͏ ͏ ͏ ͏ ͏ ͏ ͏ ͏ ͏ ͏ ͏ ͏ ͏ ͏ ͏",
  "filename_base": "2026-05-08_154443_Tesla-Rerating_19e08433d10ae0c3_e0659b12",
  "raw_path": "emails/raw_eml/2026-05-08_154443_Tesla-Rerating_19e08433d10ae0c3_e0659b12.eml",
  "text_path": "emails/text_md/2026-05-08_154443_Tesla-Rerating_19e08433d10ae0c3_e0659b12.md",
  "meta_path": "emails/metadata/2026-05-08_154443_Tesla-Rerating_19e08433d10ae0c3_e0659b12.json",
  "text_chars": 1926,
  "raw_bytes": 53802,
  "sizeEstimate": 53802,
  "attachments": []
}
