{
  "messageId": "19f473f47751a974",
  "threadId": "19f473f47751a974",
  "display_url": "https://mail.google.com/mail/u/0/#inbox/19f473f47751a974",
  "subject": "My Top 200 Watchlist",
  "from": "InvestAnswers <investanswers@creator.patreon.com>",
  "to": "samin@aianswer.us",
  "cc": "",
  "date_header": "Thu, 09 Jul 2026 14:19:15 +0000",
  "date_iso": "2026-07-09T14:19:15+00:00",
  "message_id_header": "<20260709141915.bf9ce0d10f51ede5@creator.patreon.com>",
  "labelIds": [
    "CATEGORY_PROMOTIONS",
    "UNREAD",
    "INBOX"
  ],
  "snippet": "I mentioned this list in my video yesterday and a member is interested in it. You can hit FILE, MAKE A COPY if you like. I killed some old names that ... ͏ ͏ ͏ ͏ ͏ ͏ ͏ ͏ ͏ ͏ ͏ ͏ ͏ ͏ ͏ ͏ ͏ ͏ ͏ ͏ ͏ ͏ ͏ ͏",
  "filename_base": "2026-07-09_141915_My-Top-200-Watchlist_19f473f47751a974_d7397fe4",
  "raw_path": "emails/raw_eml/2026-07-09_141915_My-Top-200-Watchlist_19f473f47751a974_d7397fe4.eml",
  "text_path": "emails/text_md/2026-07-09_141915_My-Top-200-Watchlist_19f473f47751a974_d7397fe4.md",
  "meta_path": "emails/metadata/2026-07-09_141915_My-Top-200-Watchlist_19f473f47751a974_d7397fe4.json",
  "text_chars": 2137,
  "raw_bytes": 57292,
  "sizeEstimate": 57292,
  "attachments": []
}
