{
  "messageId": "19e23202c9994dfc",
  "threadId": "19e23202c9994dfc",
  "display_url": "https://mail.google.com/mail/u/0/#inbox/19e23202c9994dfc",
  "subject": "NVDA Mkt Cap new ATH",
  "from": "InvestAnswers <investanswers@creator.patreon.com>",
  "to": "samin@aianswer.us",
  "cc": "",
  "date_header": "Wed, 13 May 2026 20:56:10 +0000",
  "date_iso": "2026-05-13T20:56:10+00:00",
  "message_id_header": "<20260513205610.bb24360b6fdb2780@creator.patreon.com>",
  "labelIds": [
    "CATEGORY_PROMOTIONS",
    "UNREAD",
    "INBOX"
  ],
  "snippet": "NVDA now worth 5.5 Trillion. NVIDIA is now worth more than the GDP of every country in the world except the USA and China.... ͏ ͏ ͏ ͏ ͏ ͏ ͏ ͏ ͏ ͏ ͏ ͏ ͏ ͏ ͏ ͏ ͏ ͏ ͏ ͏ ͏ ͏ ͏ ͏ ͏ ͏ ͏ ͏ ͏ ͏ ͏ ͏ ͏ ͏ ͏ ͏ ͏ ͏",
  "filename_base": "2026-05-13_205610_NVDA-Mkt-Cap-new-ATH_19e23202c9994dfc_3ebbe9d0",
  "raw_path": "emails/raw_eml/2026-05-13_205610_NVDA-Mkt-Cap-new-ATH_19e23202c9994dfc_3ebbe9d0.eml",
  "text_path": "emails/text_md/2026-05-13_205610_NVDA-Mkt-Cap-new-ATH_19e23202c9994dfc_3ebbe9d0.md",
  "meta_path": "emails/metadata/2026-05-13_205610_NVDA-Mkt-Cap-new-ATH_19e23202c9994dfc_3ebbe9d0.json",
  "text_chars": 1874,
  "raw_bytes": 52552,
  "sizeEstimate": 52552,
  "attachments": []
}
