{
  "messageId": "19f1dd7e10f60931",
  "threadId": "19f1dd7e10f60931",
  "display_url": "https://mail.google.com/mail/u/0/#inbox/19f1dd7e10f60931",
  "subject": "Key Takeaways from Herb/Lutz Lars Interview",
  "from": "InvestAnswers <investanswers@creator.patreon.com>",
  "to": "samin@aianswer.us",
  "cc": "",
  "date_header": "Wed, 01 Jul 2026 13:21:52 +0000",
  "date_iso": "2026-07-01T13:21:52+00:00",
  "message_id_header": "<20260701132152.ce938961e8ed6fc8@creator.patreon.com>",
  "labelIds": [
    "UNREAD",
    "CATEGORY_UPDATES",
    "INBOX"
  ],
  "snippet": "• Cybercab production will scale far beyond current expectations.• The Cybercab manufacturing line is 90% automated.• Tesla will produce more Cybercab... ͏ ͏ ͏ ͏ ͏ ͏ ͏ ͏ ͏ ͏ ͏ ͏ ͏ ͏ ͏ ͏ ͏ ͏ ͏ ͏ ͏ ͏ ͏ ͏",
  "filename_base": "2026-07-01_132152_Key-Takeaways-from-HerbLutz-Lars-Interview_19f1dd7e10f60931_395acfea",
  "raw_path": "emails/raw_eml/2026-07-01_132152_Key-Takeaways-from-HerbLutz-Lars-Interview_19f1dd7e10f60931_395acfea.eml",
  "text_path": "emails/text_md/2026-07-01_132152_Key-Takeaways-from-HerbLutz-Lars-Interview_19f1dd7e10f60931_395acfea.md",
  "meta_path": "emails/metadata/2026-07-01_132152_Key-Takeaways-from-HerbLutz-Lars-Interview_19f1dd7e10f60931_395acfea.json",
  "text_chars": 2889,
  "raw_bytes": 54226,
  "sizeEstimate": 54226,
  "attachments": []
}
